<dataConfig>
  <dataSource type="JdbcDataSource" 
              driver="org.postgresql.Driver"
              url="jdbc:postgresql://localhost/acl_production" 
              user="antho" 
              password="kC!@#$%^"/>
  <!-- <script>
    <![CDATA[
      function appendName(row) {
        var name = "";
        name += row.get('first_name') + ' ';
        name += row.get('last_name');
        row.put('author', name);
        return row; 
      }
    ]]>
  </script> -->
  <document>
    <!-- <entity name="Person" 
            query="SELECT * FROM people">
            <field column="FIRST_NAME" name="first_name"/>
            <field column="LAST_NAME" name="last_name"/>

    </entity> 
    SELECT * FROM papers P, people A, papers_people PA
            WHERE P.id = PA.paper_id AND A.id = PA.person_id
  -->
    <entity name="paper"
            query="SELECT * FROM papers">
            <field column="title" name="title"/>
            <field column="title" name="title_unstem"/>
            <field column="year" name="publish_date"/>
            <field column="anthology_id" name="paper_anthology"/><!-- 
            <field column="attach_type" name="attach_type"/>
            <field column="attachment" name="attachment"/> -->
            <field column="layers" name="layers"/>
            <field column="mrf" name="mrf"/>
            <entity name="attachment" query="SELECT * FROM attachments WHERE paper_id='${paper.id}'">
              <field column="name" name="attachment"/>
              <field column="attach_type" name="attach_type"/>
              <field column="internal" name="attach_internal"/>
              <field column="url" name="attach_url"/>
            </entity>
            <entity name="person" query="SELECT * FROM papers_people PA, people A WHERE PA.person_id = A.id AND PA.paper_id='${paper.id}'">
              <field column="id" name="author_id"/>
              <field column="first_name" name="first_name"/>
              <field column="last_name" name="last_name"/>
              <field column="full_name" name="author"/>
            </entity>
            <entity name="volume"
              query="SELECT * FROM volumes WHERE id='${paper.volume_id}'">
              <field column="id" name="volume_id"/>
              <field column="title" name="volume_title"/>
              <field column="anthology_id" name="volume_anthology"/>
              <entity name="sig"
                query="SELECT * FROM sigs_volumes SV, sigs S WHERE SV.sig_id=S.id AND SV.volume_id='${volume.id}'">
                <field column="id" name="sig_id"/>
                <field column="name" name="sig_name"/>
                <field column="url" name="sig_url"/>
                <field column="sigid" name="sig_iden"/>
              </entity>
              <entity name="event"
                query="SELECT kind, venue_id, name, acronym, venue_type FROM events_volumes EV, events E, venues V WHERE EV.event_id=E.id AND V.id=E.venue_id AND EV.volume_id='${volume.id}'">
                <field column="kind" name="event_kind"/>
                <field column="venue_id" name="venue_id"/>
                <field column="name" name="venue_name"/>
                <field column="acronym" name="venue_acronym"/>
                <field column="venue_type" name="venue_type"/>
              </entity>
              <!-- <entity name="event"
                query="SELECT * FROM events_volumes EV, events E WHERE EV.event_id=E.id AND EV.volume_id='${volume.id}'">
                <field column="kind" name="event_kind"/>
                <entity name="venue"
                  query="SELECT * FROM venues WHERE id='${event.venue_id}'">
                  <field column="id" name="venue_id"/>
                  <field column="name" name="venue_name"/>
                  <field column="acronym" name="venue_acronym"/>
                </entity>
              </entity> -->
            </entity>
    </entity>
    
    <!-- <entity name="User"
            query="SELECT * FROM users">
    </entity> -->
  </document>
</dataConfig>