<?xml version="1.0" encoding="UTF-8"?>
<volume id="P00">
<paper id="1000">
 <title>Proceedings of the 38th Annual Meeting of the Association for Computational Linguistics</title>
</paper>

<paper id="1001">
  <title>Invited Talk: Processes that Shape Conversation and their Implications for Computational Linguistics</title>
  <author>Susan E. Brennan</author>
</paper>

<paper id="1002">
  <title>Invited Talk: Generic NLP Technologies: Language, Knowledge and Information Extraction</title>
  <author>Jun'ichi Tsujii</author>
</paper>

<paper id="1003">
  <title>Invited Talk: Spoken Language Technology: Where Do We Go From Here?</title>
  <author>Roger K. Moore</author>
</paper>

<paper id="1004">
  <title>Translation with Cascaded Finite State Transducers</title>
  <author>Stephan Vogel</author>
  <author>Hermann Ney</author>
</paper>

<paper id="1005">
  <title>Phrase-Pattern-based Korean to English Machine Translation using Two Level Translation Pattern Selection</title>
  <author>Jung-jae Kim</author>
  <author>Key-Sun Choi</author>
  <author>Young-Soog Chae</author>
</paper>

<paper id="1006">
  <title>A Maximum Entropy/Minimum Divergence Translation Model</title>
  <author>George Foster</author>
</paper>

<paper id="1007">
  <title>Incorporating Compositional Evidence in Memory-Based Partial Parsing</title>
  <author>Yuval Krymolowski</author>
  <author>Ido Dagan</author>
</paper>

<paper id="1008">
  <title>Tree-gram Parsing: Lexical Dependencies and Structural Relations</title>
  <author>K. Sima'an</author>
</paper>

<paper id="1009">
  <title>An Improved Parser for Data-Oriented Lexical-Functional Analysis</title>
  <author>Rens Bod</author>
</paper>

<paper id="1010">
  <title>Robust Temporal Processing of News</title>
  <author>Inderjeet Mani</author>
  <author>George Wilson</author>
</paper>

<paper id="1011">
  <title>Tagging Unknown Proper Names Using Decision Trees</title>
  <author>Fr&#233;d&#233;ric B&#233;chet</author>
  <author>Alexis Nasr</author>
  <author>Franck Genet</author>
</paper>

<paper id="1012">
  <title>The Order of Prenominal Adjectives in Natural Language Generation</title>
  <author>Robert Malouf</author>
</paper>

<paper id="1013">
  <title>Spoken Dialogue Management Using Probabilistic Reasoning</title>
  <author>Nicholas Roy</author>
  <author>Joelle Pineau</author>
  <author>Sebastian Thrun</author>
</paper>

<paper id="1014">
  <title>An Unsupervised Approach to Prepositional Phrase Attachment using Contextually Similar Words</title>
  <author>Patrick Pantel</author>
  <author>Dekang Lin</author>
</paper>

<paper id="1015">
  <title>A Unified Statistical Model for the Identification of English BaseNP</title>
  <author>Endong Xun</author>
  <author>Changning Huang</author>
  <author>Ming Zhou</author>
</paper>

<paper id="1016">
  <title>Rule Writing or Annotation: Cost-efficient Resource Usage for Base Noun Phrase Chunking</title>
  <author>Grace Ngai</author>
  <author>David Yarowsky</author>
</paper>

<paper id="1017">
  <title>Using Existing Systems to Supplement Small Amounts of Annotated Grammatical Relations Training Data</title>
  <author>Alexander Yeh</author>
</paper>

<paper id="1018">
  <title>Distributing Representation for Robust Interpretation of Dialogue Utterances</title>
  <author>David Milward</author>
</paper>

<paper id="1019">
  <title>Can Nominal Expressions Achieve Multiple Goals?: An Empirical Study</title>
  <author>Pamela Jordan</author>
</paper>

<paper id="1020">
  <title>An Empirical Study of the Influence of Argument Conciseness on Argument Effectiveness</title>
  <author>Giuseppe Carenini</author>
  <author>Johanna D. Moore</author>
</paper>

<paper id="1021">
  <title>Multi-Agent Explanation Strategies in Real-Time Domains</title>
  <author>Kumiko Tanaka-Ishii</author>
  <author>Ian Frank</author>
</paper>

<paper id="1022">
  <title>A Computational Approach to Zero-pronouns in Spanish</title>
  <author>Antonio Ferr&#225;ndez</author>
  <author>Jes&#250;s Peral</author>
</paper>

<paper id="1023">
  <title>Coreference for NLP Applications</title>
  <author>Thomas S. Morton</author>
</paper>

<paper id="1024">
  <title>Learning Attribute Selections for Non-Pronominal Expressions</title>
  <author>Pamela Jordan</author>
  <author>Marilyn Walker</author>
</paper>

<paper id="1025">
  <title>Finite-State Non-Concatenative Morphotactics</title>
  <author>Kenneth R. Beesley</author>
  <author>Lauri Karttunen</author>
</paper>

<paper id="1026">
  <title>A Morphologically Sensitive Clustering Algorithm for Identifying Arabic Roots</title>
  <author>Anne N. De Roeck</author>
  <author>Waleed Al-Fares</author>
</paper>

<paper id="1027">
  <title>Minimally Supervised Morphological Analysis by Multimodal Alignment</title>
  <author>David Yarowsky</author>
  <author>Richard Wicentowski</author>
</paper>

<paper id="1028">
  <title>A Constraint-based Approach to English Prosodic Constituents</title>
  <author>Ewan Klein</author>
</paper>

<paper id="1029">
  <title>Inducing Probabilistic Syllable Classes Using Multivariate Clustering</title>
  <author>Karin M&#252;ller</author>
  <author>Bernd M&#246;bius</author>
  <author>Detlef Prescher</author>
</paper>

<paper id="1030">
  <title>Modeling Local Context for Pitch Accent Prediction</title>
  <author>Shimei Pan</author>
  <author>Julia Hirschberg</author>
</paper>

<paper id="1031">
  <title>A New Statistical Approach To Chinese Pinyin Input</title>
  <author>Zheng Chen</author>
  <author>Kai-Fu Lee</author>
</paper>

<paper id="1032">
  <title>Automatic Detecting/Correcting Errors in Chinese Text by an Approximate Word-Matching Algorithm</title>
  <author>Lei Zhang</author>
  <author>Ming Zhou</author>
  <author>Changning Huang</author>
  <author>Haihua Pan</author>
</paper>

<paper id="1033">
  <title>Dependency-based Syntactic Analysis of Chinese and Annotation of Parsed Corpus</title>
  <author>Tom B.Y. Lai</author>
  <author>Changning Huang</author>
</paper>

<paper id="1034">
  <title>Part-of-Speech Tagging Based on Hidden Markov Model Assuming Joint Independence</title>
  <author>Sang-Zoo Lee</author>
  <author>Jun'ichi Tsujii</author>
  <author>Hae-Chang Rim</author>
</paper>

<paper id="1035">
  <title>Language Independent, Minimally Supervised Induction of Lexical Probabilities</title>
  <author>Silviu Cucerzan</author>
  <author>David Yarowsky</author>
</paper>

<paper id="1036">
  <title>Independence and Commitment: Assumptions for Rapid Training and Execution of Rule-based POS Taggers</title>
  <author>Mark Hepple</author>
</paper>

<paper id="1037">
  <title>An Improved Error Model for Noisy Channel Spelling Correction</title>
  <author>Eric Brill</author>
  <author>Robert C. Moore</author>
</paper>

<paper id="1038">
  <title>Query-Relevant Summarization using FAQs</title>
  <author>Adam Berger</author>
  <author>Vibhu O. Mittal</author>
</paper>

<paper id="1039">
  <title>An Algorithm for One-page Summarization of a Long Text Based on Thematic Hierarchy Detection</title>
  <author>Yoshio Nakao</author>
</paper>

<paper id="1040">
  <title>Summarizing Multilingual Spoken Negotiation Dialogues</title>
  <author>Norbert Reithinger</author>
  <author>Michael Kipp</author>
  <author>Ralf Engel and Jan Ale</author>
  <author>rsson</author>
</paper>

<paper id="1041">
  <title>Headline Generation Based on Statistical Translation</title>
  <author>Michele Banko</author>
  <author>Vibhu O. Mittal</author>
  <author>Michael J. Witbrock</author>
</paper>

<paper id="1042">
  <title>Named Entity Extraction Based on A Maximum Entropy Model and Transformation Rules</title>
  <author>Kiyotaka Uchimoto</author>
  <author>Qing Ma</author>
  <author>Masaki Murata</author>
  <author>Hiromi Ozaku</author>
  <author>Hitoshi Isahara</author>
</paper>

<paper id="1043">
  <title>Extracting Causal Knowledge from a Medical Database Using Graphical Patterns</title>
  <author>Christopher S. G. Khoo</author>
  <author>Syin Chan</author>
  <author>Yun Niu</author>
</paper>

<paper id="1044">
  <title>Difficulty Indices for the Named Entity Task in Japanese</title>
  <author>Chikashi Nobata</author>
  <author>Satoshi Sekine</author>
  <author>Jun'ichi Tsujii</author>
</paper>

<paper id="1045">
  <title>Memory-Efficient and Thread-Safe Quasi-Destructive Graph Unification</title>
  <author>Marcel P. van Lohuizen</author>
</paper>

<paper id="1046">
  <title>Processing Optimality-theoretic Syntax by Interleaved Chart Parsing and Generation</title>
  <author>Jonas Kuhn</author>
</paper>

<paper id="1047">
  <title>A Polynomial-Time Fragment of Dominance Constraints</title>
  <author>Alexander Koller</author>
  <author>Kurt Mehlhorn</author>
  <author>Joachim Niehren</author>
</paper>

<paper id="1048">
  <title>Hidden Markov Model-Based Korean Part-of-Speech Tagging Considering High Agglutinativity, Word-Spacing, and Lexical Correlativity</title>
  <author>Sang-Zoo Lee</author>
  <author>Jun'ichi Tsujii</author>
  <author>Hae-Chang Rim</author>
</paper>

<paper id="1049">
  <title>Synchronous Morphological Analysis of Grapheme and Phoneme for Japanese OCR</title>
  <author>Masaaki Nagata</author>
</paper>

<paper id="1050">
  <title>Chinese-Korean Word Alignment Based on Linguistic Comparison</title>
  <author>Jin-Xia Huang</author>
  <author>Key-Sun Choi</author>
</paper>

<paper id="1051">
  <title>Specifying the Parameters of Centering Theory: a Corpus-Based Evaluation using Text from Application-Oriented Domains</title>
  <author>M. Poesio</author>
  <author>H. Cheng</author>
  <author>R. Henschel</author>
  <author>J. Hitzeman</author>
  <author>R. Kibble</author>
  <author>R. Stevenson</author>
</paper>

<paper id="1052">
  <title>The Role of Centering Theory's Rough-Shift in the Teaching and Evaluation of Writing Skills</title>
  <author>Eleni Miltsakaki</author>
  <author>Karen Kukich</author>
</paper>

<paper id="1053">
  <title>A Hierarchical Account of Referential Accessibility</title>
  <author>Nancy Ide</author>
  <author>Dan Cristea</author>
</paper>

<paper id="1054">
  <title>Lexical Transfer Using a Vector-Space Model</title>
  <author>Eiichiro Sumita</author>
</paper>

<paper id="1055">
  <title>Using Confidence Bands for Parallel Texts Alignment</title>
  <author>Ant&#243;nio Ribeiro</author>
  <author>Gabriel Lopes</author>
  <author>Jo&#227;o Mexia</author>
</paper>

<paper id="1056">
  <title>Improved Statistical Alignment Models</title>
  <author>Franz Josef Och</author>
  <author>Hermann Ney</author>
</paper>

<paper id="1057">
  <title>Multi-Component TAG and Notions of Formal Power</title>
  <author>William Schuler</author>
  <author>David Chiang</author>
  <author>Mark Dras</author>
</paper>

<paper id="1058">
  <title>Statistical Parsing with an Automatically-Extracted Tree Adjoining Grammar</title>
  <author>David Chiang</author>
</paper>

<paper id="1059">
  <title>Corpus-Based Lexical Choice in Natural Language Generation</title>
  <author>Srinivas Bangalore</author>
  <author>Owen Rambow</author>
</paper>

<paper id="1060">
  <title>An Information-Theory-Based Feature Type Analysis for the Modeling of Statistical Parsing</title>
  <author>Zhifang Sui</author>
  <author>Jun Zhao</author>
  <author>Dekai Wu</author>
</paper>

<paper id="1061">
  <title>Lexicalized Stochastic Modeling of Constraint-Based Grammars using Log-Linear Measures and EM Training</title>
  <author>Stefan Riezler</author>
  <author>Detlef Prescher</author>
  <author>Jonas Kuhn</author>
  <author>Mark Johnson</author>
</paper>

<paper id="1062">
  <title>Utilizing the World Wide Web as an Encyclopedia: Extracting Term Descriptions from Semi-Structured Texts</title>
  <author>Atsushi Fujii</author>
  <author>Tetsuya Ishikawa</author>
</paper>

<paper id="1063">
  <title>Term Recognition Using Technical Dictionary Hierarchy</title>
  <author>Jong-Hoon Oh</author>
  <author>KyungSoon Lee</author>
  <author>Key-Sun Choi</author>
</paper>

<paper id="1064">
  <title>Mapping WordNets Using Structural Information</title>
  <author>J. Daud&#233;</author>
  <author>L. Padr&#243;</author>
  <author>G. Rigau</author>
</paper>

<paper id="1065">
  <title>Automatic Labeling of Semantic Roles</title>
  <author>Daniel Gildea</author>
  <author>Daniel Jurafsky</author>
</paper>

<paper id="1066">
  <title>Feature Logic for Dotted Types: A Formalism for Complex Word Meanings</title>
  <author>Manfred Pinkal</author>
  <author>Michael Kohlhase</author>
</paper>

<paper id="1067">
  <title>PENS: A Machine-aided English Writing System for Chinese Users</title>
  <author>Ting Liu</author>
  <author>Ming Zhou</author>
  <author>Jianfeng Gao</author>
  <author>Endong Xun</author>
  <author>Changning Huang</author>
</paper>

<paper id="1068">
  <title>Diagnostic Processing of Japanese for Computer-Assisted Second Language Learning</title>
  <author>Jun'ichi Kakegawa</author>
  <author>Hisayuki Kanda</author>
  <author>Eitaro Fujioka</author>
  <author>Makoto Itami</author>
  <author>Kohji Itoh</author>
</paper>

<paper id="1069">
  <title>Word Sense Disambiguation by Learning from Unlabeled Data</title>
  <author>Seong-Bae Park</author>
  <author>Byoung-Tak Zhang</author>
  <author>Yung Taek Kim</author>
</paper>

<paper id="1070">
  <title>Importance of Pronominal Anaphora Resolution in Question Answering Systems</title>
  <author>Jos&#233; L. Vicedo</author>
  <author>Antonio Ferr&#225;ndez</author>
</paper>

<paper id="1071">
  <title>The Structure and Performance of an Open-Domain Question Answering System</title>
  <author>Dan Moldovan</author>
  <author>Sanda Harabagiu</author>
  <author>Marius Pasca</author>
  <author>Rada Mihalcea</author>
  <author>Roxana Girju</author>
  <author>Richard Goodrum</author>
  <author>Vasile Rus</author>
</paper>

<paper id="1072">
  <title>Dimension-Reduced Estimation of Word Co-occurrence Probability</title>
  <author>Kilyoun Kim</author>
  <author>Key-Sun Choi</author>
</paper>

<paper id="1073">
  <title>Distribution-Based Pruning of Backoff Language Models</title>
  <author>Jianfeng Gao</author>
  <author>Kai-Fu Lee</author>
</paper>

<paper id="1074">
  <title>Panel: Computational Linguistics Research on Philippine Languages</title>
  <author>Rachel Edita O. Roxas</author>
  <author>Allan Borra</author>
</paper>

<paper id="1075">
  <title>Panel: Development of Computational Linguistics Research: A Challenge for Indonesia</title>
  <author>Bobby Nazief</author>
</paper>

<paper id="1076">
  <title>Panel: Good Spelling of Vietnamese Texts,One Aspect of Computational Linguistics in Vietnam</title>
  <author>Huy Khanh Phan</author>
</paper>

<paper id="1077">
  <title>Panel: Computational Linguistics in India: An Overview</title>
  <author>Akshar Bharati</author>
  <author>Vineet Chaitanya</author>
  <author>Rajeev Sangal</author>
</paper>

<paper id="1078">
  <title>Panel: The State of the Art in Thai Language Processing</title>
  <author>Virach Sornlertlamvanich</author>
  <author>Tanapong Potipiti</author>
  <author>Chai Wutiwiwatchai</author>
  <author>Pradit Mittrapiyanuruk</author>
</paper>

<paper id="1079">
  <title>Panel: Computational Linguistics in Malaysia</title>
  <author>Zaharin Yusoff</author>
</paper>
</volume>
