<volume id="P84">
 <paper id="1000">
 <title>10th International Conference on Computational Linguistics and 22nd Annual Meeting of the Association for Computational Linguistics</title>
</paper>

 <paper id="1001">
 <title>Multilingual Text Processing in a Two-Byte Code</title>
 <author><first>Lloyd B.</first><last>Anderson</last></author>
</paper>

 <paper id="1002">
 <title>CONVEYING IMPLICIT CONTENT IN NARRATIVE SUMMARIES</title>
 <author><first>Malcolm E.</first><last>Cook</last></author>
 <author><first>Wendy G.</first><last>Lehnert</last></author>
 <author><first>David D.</first><last>McDonald</last></author>
</paper>

 <paper id="1003">
 <title>TRANSFORMING ENGLISH INTERFACES TO OTHER NATURAL LANGUAGES: AN EXPERIMENT WITH PORTUGUESE</title>
 <author><first>ABRIEL PEREIRA</first><last>LOPES</last></author>
</paper>

 <paper id="1004">
 <title>UN OUTIL MULTIDIMENSIONNEL DE L’ANALYSE DU DISCOURS</title>
 <author><first>J.</first><last>CHAUCAE</last></author>
</paper>

 <paper id="1005">
 <title>A STOCHASTIC APPROACH TO SENTENCE PARSING</title>
 <author><first>Tetsunosuke</first><last>Fujisaki</last></author>
</paper>

 <paper id="1006">
 <title>BOUNDED CONTEXT PARSING AND EASY LEARNABIITY</title>
 <author><first>Robert C.</first><last>Berwick</last></author>
</paper>

 <paper id="1007">
 <title>THE REPRESENTATION OF CONSTITUENT STRUCTURES FOR FINITE-STATE PARSING</title>
 <author><first>D. Terence</first><last>Langendoen</last></author>
 <author><first>Yedidyah</first><last>Langsam</last></author>
</paper>

 <paper id="1008">
 <title>Features and Values</title>
 <author><first>Lauri</first><last>Karttunen</last></author>
</paper>

 <paper id="1009">
 <title>APPLICATIONS OF A LEXICOGRAPHICAL DATA BASE FOR GERMAN</title>
 <author><first>Wolfgang</first><last>Teubert</last></author>
</paper>

 <paper id="1010">
 <title>DENORMALIZATION AND CROSS REFERENCING IN THEORETICAL LEXICOGRAPHY</title>
 <author><first>Joseph E.</first><last>Grimes</last></author>
</paper>

 <paper id="1011">
 <title>Lexicon Features for Japanese Syntactic Analysis in Mu-Project-JE</title>
 <author><first>Yoshiyuki</first><last>Sakamoto</last></author>
 <author><first>Masayuki</first><last>Satoh</last></author>
 <author><first>Tetsuya</first><last>Ishikawa</last></author>
</paper>

 <paper id="1012">
 <title>Toward a Redefinition of Yes/No Questions</title>
 <author><first>Julia</first><last>Hirschberg</last></author>
</paper>

 <paper id="1013">
 <title>THE SYNTAX AND SEMANTICS OF USER-DEFINED MODIFIERS IN TRANSPORTABLE NATURAL LANGUAGE PROCESSOR</title>
 <author><first>Bruce W.</first><last>Ballard</last></author>
</paper>

 <paper id="1014">
 <title>Interaction of Knowledge Sources in a Portable Natural Language Interface</title>
 <author><first>Carole D.</first><last>Hafner</last></author>
</paper>

 <paper id="1015">
 <title>USES OF C-GPAPHS IN A PROTOTYPE FOR ALTOMATIC TWISLATION</title>
 <author><first>Marco A.</first><last>CLEMENTE-SALAZAR</last></author>
</paper>

 <paper id="1016">
 <title>QUASI-INDEXICAL REFERENCE IN PROPOSITIONAL SEMANTIC NETWORKS</title>
 <author><first>William J.</first><last>Rapaport</last></author>
 <author><first>Stuart C.</first><last>Shapiro</last></author>
</paper>

 <paper id="1017">
 <title>The Costs of Inheritance in Semantic Networks</title>
 <author><first>Rob’t F.</first><last>Sinlnlons</last></author>
</paper>

 <paper id="1018">
 <title>FUNCTIONAL UNIFICATION GRAMMAR: A FORMALISM FOR MACHINE TRANSLATION</title>
 <author><first>Martin</first><last>Kay</last></author>
</paper>

 <paper id="1019">
 <title>COMPUTER SIMULATION OF SPONTANEOUS SPEECH PRODUCTION</title>
 <author><first>Bengt</first><last>Sigurd</last></author>
</paper>

 <paper id="1020">
 <title>LIMITED DOMAIN SYSTEMS FOR LANGUAGE TEACHING</title>
 <author><first>S G</first><last>Pulman</last></author>
</paper>

 <paper id="1021">
 <title>GTT : A GENERAL TRANSDUCER FOR TEACHING COMPUTATIONAL LINGUISTICS</title>
 <author><first>P.</first><last>Shane</last></author>
 <author><first>J.L.</first><last>Cochard</last></author>
</paper>

 <paper id="1022">
 <title>A PARSING ARCHITECTURE BASED ON DISTRIBUTED MEMORY MACHINES</title>
 <author><first>Jon M.</first><last>Slack</last></author>
</paper>

 <paper id="1023">
 <title>AUTOMATED DETERMINATION OF SUBLANGUAGE SYNTACTIC USAGE</title>
 <author><first>Ralph</first><last>Grishman</last></author>
 <author><first>Ngo Thanh</first><last>Nhan</last></author>
 <author><first>Elate</first><last>Marsh</last></author>
 <author><first>Lyneae</first><last>Hirschman</last></author>
</paper>

 <paper id="1024">
 <title>Semantic Interpretation Using KL-ONE</title>
 <author><first>Norman K.</first><last>Sondheimer</last></author>
 <author><first>Ralph M.</first><last>Weischedel</last></author>
 <author><first>Robert J.</first><last>Bobrow</last></author>
</paper>

 <paper id="1025">
 <title>TWO THEORIES FOR COMPUTING THE LOGICAL FORM OF MASS EXPRESSIONS</title>
 <author><first>Francis Jeffry</first><last>Pelletier</last></author>
 <author><first>Lenhart K.</first><last>Schubert</last></author>
</paper>

 <paper id="1026">
 <title>SYNTACTIC AND SEMANTIC PARSABILITY</title>
 <author><first>Geoffrey K.</first><last>Pullum</last></author>
</paper>

 <paper id="1027">
 <title>The Semantics of Grammar Formalisms Seen as Computer Languages</title>
 <author><first>Fernando C. N.</first><last>Pereira</last></author>
 <author><first>Stuart M.</first><last>Shieber</last></author>
</paper>

 <paper id="1028">
 <title>THE RESOLUTION OF QUANTIFICATIONAL AMBIGUITY IN THE TENDUM SYSTEM</title>
 <author><first>Harry</first><last>Bunt</last></author>
</paper>

 <paper id="1029">
 <title>Preventing False Inferences</title>
 <author><first>Aravind</first><last>Joshi</last></author>
 <author><first>Bonnie</first><last>Webber</last></author>
 <author><first>Ralph M.</first><last>Weischede</last></author>
</paper>

 <paper id="1030">
 <title>PROBLEM LOCALIZATION STRATEGIES FOR PRAMATICS PROCESSING IN NATURAL-LANGUAGE FRONT ENDS</title>
 <author><first>Lance A.</first><last>Ramahaw</last></author>
 <author><first>Ralph M.</first><last>Weischedel</last></author>
</paper>

 <paper id="1031">
 <title>A CONNECTIONIST MODEL OF SOME ASPECTS OF ANAPHOR RESOLUTION</title>
 <author><first>Ronan G.</first><last>Reilly</last></author>
</paper>

 <paper id="1032">
 <title>CONCURRENT PARSING IN PROGRAMMABLE LOGIC ARRAY (PLA-) NETS PROBLEMS AND PROPOSALS</title>
 <author><first>Helmut</first><last>Schnelle</last></author>
</paper>

 <paper id="1033">
 <title>A Case Analysis Method Cooperating with ATNG and Its Application to Machine Translation</title>
 <author><first>Hitoshi</first><last>IIDA</last></author>
</paper>

 <paper id="1034">
 <title>A PROPER TREATMEMT OF SYNTAX AND SEMANTICS IN MACHINE TRANSLATION</title>
 <author><first>Yoshihiko</first><last>Nitta</last></author>
 <author><first>Atsushi</first><last>Okajima</last></author>
 <author><first>Hiroyuki</first><last>Kaji</last></author>
 <author><first>Youichi</first><last>Hidano</last></author>
 <author><first>Koichiro</first><last>Ishihara</last></author>
</paper>

 <paper id="1035">
 <title>A CONSIDERATION ON THE CONCEPTS STRUCTURE AND LANGUAGE- IN RELATION TO SELECTIONS OF TRANSLATION EQUIVALENTS OF VERBS IN MACHINE TRANSLATION SYSTEM</title>
 <author><first>Sho</first><last>Yoshida</last></author>
</paper>

 <paper id="1036">
 <title>DETECTING PATTERNS IN A LEXICAL DATA BASE</title>
 <author><first>Nicoletta</first><last>Calzolari</last></author>
</paper>

 <paper id="1037">
 <title>LINGUISTIC PROBLEMS IN MULTILINGUAL MORPHOLOGICAL DECOMPOSITION</title>
 <author><first>G.Thurmair</first><last>Siemens</last></author>
</paper>

 <paper id="1038">
 <title>A GENERAL COMPUTATIONAL MODEL FOR WORD-FORM RECOGNITION AND PRODUCTION</title>
 <author><first>Kimmo</first><last>Koskenniemi</last></author>
</paper>

 <paper id="1039">
 <title>PANEL: NATURAL LANGUAGE AND DATABASES, AGAIN</title>
 <author><first>Karen Sparck</first><last>Jones</last></author>
</paper>

 <paper id="1040">
 <title>THERE STILL IS GOLD IN THE DATABASE MINE</title>
 <author><first>Madeleine</first><last>Bates</last></author>
</paper>

 <paper id="1041">
 <title>Is There Natural Language after Data Bases?</title>
 <author><first>Jaime G.</first><last>Carbonell</last></author>
</paper>

 <paper id="1042">
 <title>Panel on Natural Language and Databases</title>
 <author><first>Daniel P.</first><last>Flickinger</last></author>
</paper>

 <paper id="1043">
 <title>Natural Language for Exert Systems: Comparisons with Database Systems</title>
 <author><first>Kathleen R.</first><last>McKeown</last></author>
</paper>

 <paper id="1044">
 <title>REPRESENTING KNOWLEDGE ABOUT KNOWLEDGE AND MUTUAL KNOWLEDGE</title>
 <author><first>Said</first><last>Soulhi</last></author>
</paper>

 <paper id="1045">
 <title>UNDERSTANDING PRAGMATICALLY ILL-FORMED INPUT</title>
 <author><first>M. Sandra</first><last>Carberry</last></author>
</paper>

 <paper id="1046">
 <title>Referring as Requesting</title>
 <author><first>Philip R.</first><last>Cohen</last></author>
</paper>

 <paper id="1047">
 <title>Entity-Oriented Parsing</title>
 <author><first>Philip J.</first><last>Hayes</last></author>
</paper>

 <paper id="1048">
 <title>Combining Functionality and Object- Orientedness for Natural Language Processing</title>
 <author><first>Toyoaki</first><last>Nishidal</last></author>
 <author><first>Shuji</first><last>Doshita</last></author>
</paper>

 <paper id="1049">
 <title>USE OF HEURISTIC KNOWLEDGE IN CHINESE LANGUAGE ANALYSIS</title>
 <author><first>Yiming</first><last>Yang</last></author>
 <author><first>Toyoaki NishidaShuji</first><last>Doshita</last></author>
</paper>

 <paper id="1050">
 <title>THE DESIGN OF THE KERNEL ARCHITECTURE FOR THE EUROTRA* SOFTWARE</title>
 <author><first>R.L.</first><last>Johnson</last></author>
 <author><first>M.A.</first><last>Rosner</last></author>
</paper>

 <paper id="1051">
 <title>MACHINE TRANSLATION : WHAT TYPE OF POST-EDITING ON WHAT TYPE OF DOCUMENTS FOR WHAT TYPE OF USERS</title>
 <author><first>Anne-Marie</first><last>LAURIAN</last></author>
</paper>

 <paper id="1052">
 <title>Simplifying Deterministic Parsing</title>
 <author><first>Alan W.</first><last>Carter</last></author>
 <author><first>Michael J.</first><last>Frelling</last></author>
</paper>

 <paper id="1053">
 <title>DEALING WITH CONJUNCTIONS IN A MACHINE TRANSLATION ENVIRONMENT</title>
 <author><first>Xiuming</first><last>HUANG</last></author>
</paper>

 <paper id="1054">
 <title>ON PARSING PREFERENCES</title>
 <author><first>Lenhart K.</first><last>Schubert</last></author>
</paper>

 <paper id="1055">
 <title>A COMPUTATIONAL THEORY OF THE FUNCTION OF CLUE WORDS IN ARGIJMENT UNDERSTANDING</title>
 <author><first>Robin</first><last>Cohen</last></author>
</paper>

 <paper id="1056">
 <title>CONTROL STRUCTURES AND THEORIES OF INTERACTION IN SPEECII UNDER STANDING SYSTEMS</title>
 <author><first>E.J.</first><last>Briscoe</last></author>
 <author><first>H.K.</first><last>Boguraev</last></author>
</paper>

 <paper id="1057">
 <title>Analysis Grammar of Japanese in the Mu-project - A Procedural Approach to Analysis Grammar</title>
 <author><first>Jun-ichi</first><last>TSUJII</last></author>
 <author><first>Jun-ichi</first><last>NAKAMURA</last></author>
 <author><first>Makoto</first><last>NAGAO</last></author>
</paper>

 <paper id="1058">
 <title>LEXICON-GRAMMAR AND THE SYNTACTIC ANALYSIS OF FRENCH</title>
 <author><first>Maurice</first><last>Gross</last></author>
</paper>

 <paper id="1059">
 <title>Building a Large Knowledge Base for a Natural Language System</title>
 <author><first>Jerry R.</first><last>Hobbs</last></author>
</paper>

 <paper id="1060">
 <title>LINGUISTICALLY MOTIVATED DESCRIPTIVE TERM SELECTION</title>
 <author><first>K. Sparck</first><last>Jones</last></author>
 <author><first>J.I.</first><last>Tait</last></author>
</paper>

 <paper id="1061">
 <title>INFERENCING ON LINGUISTICALLY BASED SEMANTIC STRUCTURES</title>
 <author><first>Eva</first><last>Ilajicova</last></author>
 <author><first>Milena</first><last>Hnatkova</last></author>
</paper>

 <paper id="1062">
 <title>SEMANTIC RELEVANCE AND ASPECT DEPENDENCY IN A GIVEN SUBJECT DOMAIN Contents-driven algorithmic processing of fuzzy wordmeanings to form dynamic stereotype representations</title>
 <author><first>Arbeitsgruppe</first><last>German</last></author>
 <author><first>Burghard B.</first><last>Rieger</last></author>
</paper>

 <paper id="1063">
 <title>A Plan Recognition Model for Clarification Subdialogues</title>
 <author><first>Diane J.</first><last>Litman</last></author>
 <author><first>James F.</first><last>Allen</last></author>
</paper>

 <paper id="1064">
 <title>A COMPUTATIONAL THEORY OF DISPOSITIONS</title>
 <author><first>Lotfi A.</first><last>Zadeh</last></author>
</paper>

 <paper id="1065">
 <title>Using Focus to Generate Complex and Simple Sentences</title>
 <author><first>Marcia A.</first><last>Derr</last></author>
 <author><first>Kathleen R.</first><last>McKeown</last></author>
</paper>

 <paper id="1066">
 <title>A RATIONAL RECONSTRUCTION OF THE PROTEUS SENTENCE PLANNER</title>
 <author><first>Graeme</first><last>Ritchie</last></author>
</paper>

 <paper id="1067">
 <title>SOFTWARE TOOLS FOR THE ENVIRONMENT OF A COMPUTER AIDED TRANSLATION SYSTEM</title>
 <author><first>Daniel</first><last>BACHUT</last></author>
 <author><first>Nelson</first><last>VERASTEGUI</last></author>
</paper>

 <paper id="1068">
 <title>DESIGN OF A MACHINE TRANSLATION SYSTEM FOR A SUBLANGUAGE</title>
 <author><first>Beat</first><last>Buchmann</last></author>
 <author><first>Susan</first><last>Warwick</last></author>
 <author><first>Patrick</first><last>Shane</last></author>
</paper>

 <paper id="1069">
 <title>Grammar Writing System (GRADE) of Mu-Machine Translation Project and its Characteristics</title>
 <author><first>Jun-ichi</first><last>NAKAMURA</last></author>
 <author><first>Jun-ichi</first><last>TSUJII</last></author>
 <author><first>Makoto</first><last>NAGAO</last></author>
</paper>

 <paper id="1070">
 <title>A DISCOVERY PROCEDURE FOR CERTAIN PHONOLOGICAL RULES</title>
 <author><first>Mark</first><last>Johnson</last></author>
</paper>

 <paper id="1071">
 <title>WHAT NOT TO SAY</title>
 <author><first>Jan</first><last>Fornell</last></author>
</paper>

 <paper id="1072">
 <title>WHEN IS THE NEXT ALPAC REPORT DUE?</title>
 <author><first>Margaret</first><last>KING</last></author>
</paper>

 <paper id="1073">
 <title>LR Parsers For Natural Languages</title>
 <author><first>Masaru</first><last>Tomita</last></author>
</paper>

 <paper id="1074">
 <title>LFG System in Prolog </title>
 <author><first>Hidekl</first><last>Yasukawa</last></author>
</paper>

 <paper id="1075">
 <title>The Design of a Computer Language for Linguistic Information </title>
 <author><first>Stuart M.</first><last>Shieber</last></author>
</paper>

 <paper id="1076">
 <title>Discourse Structures for Text Generation </title>
 <author><first>William C.</first><last>Mann</last></author>
</paper>

 <paper id="1077">
 <title>Semantic Rule Based Text Generation </title>
 <author><first>Michael L.</first><last>Mauldin</last></author>
</paper>

 <paper id="1078">
 <title>Controlling Lexical Substitution in Computer Text Generation</title>
 <author><first>Robert</first><last>Granville</last></author>
</paper>

 <paper id="1079">
 <title>UNDERSTANDING OF  JAPANESE IN AN INTERACTIVE PROGRAMMING SYSTEM</title>
 <author><first>Kenji</first><last>Sugiyama</last></author>
 <author><first>Masayuki</first><last>Kameda</last></author>
 <author><first>Kouji</first><last>Akiyama</last></author>
</paper>

 <paper id="1080">
 <title>TWO-WAY FINITE AUTOMATA AND DEPENDENCY GRAMMAR: A PARSING METHOD FOR INFLECTIONAL FREE WORD ORDER LANGUAGES</title>
 <author><first>Esa</first><last>Nelimarkka</last></author>
 <author><first>Harri</first><last>Jappinen</last></author>
 <author><first>Aarno</first><last>Lehtola</last></author>
</paper>

 <paper id="1081">
 <title>INTERRUPTABLE TRANSITION NETWORKS </title>
 <author><first>Sergei</first><last>Nirenburg</last></author>
</paper>

 <paper id="1082">
 <title>AUTOMATIC CONSTRUCTION OF DISCOURSE REPRESENTATION STRUCTURES </title>
 <author><first>Franz</first><last>Guenthner</last></author>
</paper>

 <paper id="1083">
 <title>TEXTUAL EXPERTISE IN WORD EXPERTS: AN APPROACH TO TEXT PARSING BASED ON TOPIC/COMMENT MONITORING</title>
 <author><first>Udo</first><last>Hahn</last></author>
</paper>

 <paper id="1084">
 <title>SOME LINGUISTIC ASPECTS FOR AUTOMATIC TEXT UNDERSTANDING</title>
 <author><first>Yutaka</first><last>Kusanagi</last></author>
</paper>

 <paper id="1085">
 <title>A SYNTACTIC APPROACH TO DISCOURSE SEMANTICS </title>
 <author><first>Livia</first><last>Polanyi</last></author>
 <author><first>Remko</first><last>Scha</last></author>
</paper>

 <paper id="1086">
 <title>DEALING WITH INCOMPLETENESS OF LINGUISTIC KNOWLEDGE IN LANGUAGE TRANSLATION – TRANSFER AND GENERATION STAGE OF MU MACHINE TRANSLATION PROJECT</title>
 <author><first>Makoto</first><last>Nagao</last></author>
 <author><first>Toyoaki</first><last>Nishida</last></author>
 <author><first>Jun-ichi</first><last>Tsujii</last></author>
</paper>

 <paper id="1087">
 <title>LEXICAL SEMANTICS IN HUMAN-COMPUTER COMMUNICATION </title>
 <author><first>Jarrett</first><last>Rosenberg</last></author>
</paper>

 <paper id="1088">
 <title>A Response to the Need for Summary Responses</title>
 <author><first>J.K.</first><last>Kalita</last></author>
 <author><first>M.J.</first><last>Colbourn</last></author>
 <author><first>G.I.</first><last>McCalla</last></author>
</paper>

 <paper id="1089">
 <title>Coping with Extragrammaticality </title>
 <author><first>Jaime G.</first><last>Carbonell</last></author>
 <author><first>Philip J.</first><last>Hayes</last></author>
</paper>

 <paper id="1090">
 <title>Correcting Object-Related Misconceptions: How Should The System Respond?</title>
 <author><first>Kathleen F.</first><last>McCoy</last></author>
</paper>

 <paper id="1091">
 <title>AN ALGORITHM FOR IDENTIFYING COGNATES BETWEEN RELATED LANGUAGES</title>
 <author><first>Jacques</first><last>B.M.Guy</last></author>
</paper>

 <paper id="1092">
 <title>From HOPE en I’ESPERANCE On the Role of Computational Neurolinguistics in Cross-Language Studies</title>
 <author><first>Helen M.</first><last>Gigley</last></author>
</paper>

 <paper id="1093">
 <title>MACHINE-READABLE DICTIONARIES</title>
 <author><first>Donald E.</first><last>Walker</last></author>
</paper>

 <paper id="1094">
 <title>LEXICAL KNOWLEDGE BASES</title>
 <author><first>Robert A.</first><last>Amsler</last></author>
</paper>

 <paper id="1095">
 <title>MACHINE-READABLE DICTIONARIES, LEXICAL DATA BASES AND THE LEXICAL SYSTEM</title>
 <author><first>Nicoletta</first><last>Calsolari</last></author>
</paper>

 <paper id="1096">
 <title>THE DICTIONARY SERVER</title>
 <author><first>Martin</first><last>Kay</last></author>
</paper>

 <paper id="1097">
 <title>HOW TO MISREAD A DICTIONARY</title>
 <author><first>George A.</first><last>Miller</last></author>
</paper>

 <paper id="1098">
 <title>MACHINE-READABLE COMPONENTS IN A VARIETY OF INFORMATION-SYSTEM APPLICATIONS</title>
 <author><first>Howard R.</first><last>Webber</last></author>
</paper>

 <paper id="1099">
 <title>TRANSFER IN A MULTILINGUAL MT SYSTEM </title>
 <author><first>Steven</first><last>Krauwer</last></author>
 <author><first>Louis</first><last>des Tombe</last></author>
</paper>

 <paper id="1100">
 <title>EXPERT SYSTEMS AND OTHER NEW TECHNIQUES IN MT SYSTEMS</title>
 <author><first>Christian</first><last>BOITET</last></author>
 <author><first>Rene</first><last>GERBER</last></author>
</paper>

 <paper id="1101">
 <title>ROBUST PROCESSING IN MACHINE TRANSLATION </title>
 <author><first>Doug</first><last>Arnold</last></author>
 <author><first>Rod</first><last>Johnson</last></author>
</paper>

 <paper id="1102">
 <title>Disambiguating Grammatically Ambiguous Sentences By Asking</title>
 <author><first>Masaru</first><last>Tornita</last></author>
</paper>

 <paper id="1103">
 <title>AMBIGUITY RESOLUTION IN THE HUMAN SYNTACTIC PARSER” AN EXPERIMENTAL STUDY</title>
 <author><first>Howard S.</first><last>Kurtzman</last></author>
</paper>

 <paper id="1104">
 <title>Conceptual Analysis of Garden-Path Sentences</title>
 <author><first>Michael J.</first><last>Pazzani</last></author>
</paper>

 <paper id="1105">
 <title>LANGUAGE GENERATION FROM CONCEPTUAL STRUCTURE: SYNTHESIS OF GERMAN IN A JAPANESE/GERMAN MT PROJECT</title>
 <author><first>J.</first><last>Laubsch</last></author>
 <author><first>D.</first><last>Roesner</last></author>
 <author><first>K.</first><last>Hanakata</last></author>
 <author><first>A.</first><last>Lesnlewski</last></author>
</paper>

 <paper id="1106">
 <title>Natural Language driven Image Generation </title>
 <author><first>Giovanni</first><last>Adorni</last></author>
 <author><first>Mauro Di</first><last>Manzo</last></author>
 <author><first>Fausto</first><last>Giunchiglia</last></author>
</paper>

 <paper id="1107">
 <title>Conceptual and Linguistic Decisions in Generation</title>
 <author><first>Laurence</first><last>DANLOS</last></author>
</paper>

 <paper id="1108">
 <title>A Computational Analysis of Complex Noun Phrases in Navy Messages </title>
 <author><first>Elaine</first><last>Marsh</last></author>
</paper>

 <paper id="1109">
 <title>ANOTHER LOOK AT NOMINAL COMPOUNDS</title>
 <author><first>Pierre</first><last>Isabelle</last></author>
</paper>

 <paper id="1110">
 <title>SEMANTIC PARSING AS GRAPH LANGUAGE TRANSFORMATION - A MULTIDIMENSIONAL APPROACH TO PARSING HIGHLY INFLECTIONAL LANGUAGES</title>
 <author><first>Eero</first><last>Hyvonen</last></author>
</paper>

 <paper id="1111">
 <title>HANDLING SYNTACTICAL AMBIGUITY IN MACHINE TRANSLATION</title>
 <author><first>Vladimir</first><last>Pericliev</last></author>
</paper>

 <paper id="1112">
 <title>ARGUMENTATION IN REPRESENTATION SEMANTICS</title>
 <author><first>Pierre-Yves</first><last>RACCAH</last></author>
</paper>

 <paper id="1113">
 <title>VOICE SIMULATION: FACTORS AFFECTING QUALITY AND NATURALNESS</title>
 <author><first>B.</first><last>Yegnanarayana</last></author>
 <author><first>J.M.</first><last>Naik</last></author>
 <author><first>D.G.</first><last>Childers</last></author>
</paper>

 <paper id="1114">
 <title>INTERPRETING SYNTACTICALLY ILL-FORMED SENTENCES</title>
 <author><first>Leonardo</first><last>LESMO</last></author>
 <author><first>Pietro</first><last>TORASSO</last></author>
</paper>

 <paper id="1115">
 <title>AN INTONATIONAL DELPHI POLL ON FUTURE TRENDS IN “INFORMATION LINGUISTICS”</title>
 <author><first>Rainer</first><last>Kuhlen</last></author>
</paper>

 <paper id="1116">
 <title>Machine Translation: its History, Current Status, and Future Prospects</title>
 <author><first>Jonathan</first><last>Slocum</last></author>
</paper>

</volume>