<?xml version="1.0" encoding="UTF-8"?>
<volume id="T87">
 <paper id="1000">
 <title>Theoretical Issues in Natural Language Processing 3</title>
</paper>

 <paper id="1001">
 <title>Tinlap3</title>
</paper>

 <paper id="1002">
 <title>Program for Tinlap3</title>
</paper>

 <paper id="1003">
 <title>The Panels</title>
</paper>

 <paper id="1004">
 <title>THE DEFINITIONAL POWER OF WORDS</title>
 <author><first>Branimir K.</first><last>Boguraev</last></author>
</paper>

 <paper id="1005">
 <title>WORDS AND WORLDS</title>
 <author><first>Robert A.</first><last>Amsler</last></author>
</paper>

 <paper id="1006">
 <title>World Knowledge and Word Meaning</title>
 <author><first>Jerry R.</first><last>Hobbs</last></author>
</paper>

 <paper id="1007">
 <title>THE BOUNDARY BETWEEN WORD KNOWLEDGE AND WORLD KNOWLEDGE</title>
 <author><first>Judy</first><last>Kegl</last></author>
</paper>

 <paper id="1008">
 <title>Information, Unification and Locality</title>
 <author><first>Fernando C. N.</first><last>Pereira</last></author>
</paper>

 <paper id="1009">
 <title>COMIT ==> PATR II</title>
 <author><first>Gerald</first><last>Gazdar</last></author>
</paper>

 <paper id="1010">
 <title>Unification and the new grammatism</title>
 <author><first>Steve</first><last>Pulman</last></author>
</paper>

 <paper id="1011">
 <title>Unification and Some New Grammatical Formalisms</title>
 <author><first>Aravind K.</first><last>Joshi</last></author>
</paper>

 <paper id="1012">
 <title>The Linguistic Connection</title>
 <author><first>Martin</first><last>Kay</last></author>
</paper>

 <paper id="1013">
 <title>Connectionist Models: Not Just a Notational Variant Not a Panacea</title>
 <author><first>David L.</first><last>Waltz</last></author>
</paper>

 <paper id="1014">
 <title>Toward Connectionist Semantics</title>
 <author><first>Garrison W.</first><last>Cottrell</last></author>
</paper>

 <paper id="1015">
 <title>Connectionism and Explanation</title>
 <author><first>Eugene</first><last>Charniak</last></author>
</paper>

 <paper id="1016">
 <title>Parallel Distributed Processing and Role Assignment Constraints</title>
 <author><first>James L.</first><last>McClelland</last></author>
</paper>

 <paper id="1017">
 <title>Possible Implications of Connectionism</title>
 <author><first>Wendy G.</first><last>Lehner</last></author>
</paper>

 <paper id="1018">
 <title>Whither Discourse and Speech Acts?</title>
 <author><first>Barbara J.</first><last>Grosz</last></author>
</paper>

 <paper id="1019">
 <title>NO TITLE</title>
 <author><first>Julia</first><last>Hirschberg</last></author>
</paper>

 <paper id="1020">
 <title>Towards a Semantic Theory of Discourse</title>
 <author><first>C. Raymond</first><last>Perrau</last></author>
</paper>

 <paper id="1021">
 <title>A Framework for a Theory of Meaning</title>
 <author><first>Robert</first><last>Wilens</last></author>
</paper>

 <paper id="1022">
 <title>Discourse Representation Theory and the Semantics of Natural Languages: Contribution to a Panel on "Discourse Theory and Speech Acts" TINLAP3</title>
 <author><first>F.</first><last>Guenthner</last></author>
</paper>

 <paper id="1023">
 <title>Natural Language Processing: What's Really Involved?</title>
 <author><first>Roger</first><last>Schank</last></author>
 <author><first>Alex</first><last>Kass</last></author>
</paper>

 <paper id="1024">
 <title>THE RATE OF PROGRESS IN NATURAL LANGUAGE PROCESSING</title>
 <author><first>Norman K.</first><last>Sondheimer</last></author>
</paper>

 <paper id="1025">
 <title>LET'S PUT THE AI BACK IN NLP</title>
 <author><first>Lawrence</first><last>Birnbaum</last></author>
</paper>

 <paper id="1026">
 <title>On keeping logic in its place</title>
 <author><first>Yorick</first><last>Wilks</last></author>
</paper>

 <paper id="1027">
 <title>Position Paper on Common-sense and Formal Semantics</title>
 <author><first>Geoffrey</first><last>Nunberg</last></author>
</paper>

 <paper id="1028">
 <title>On Formal Versus Commonsense Semantics</title>
 <author><first>David</first><last>Israel</last></author>
</paper>

 <paper id="1029">
 <title>They say it's a new sort of engine: but the SUMP's still there</title>
 <author><first>Karen Sparck</first><last>Jones</last></author>
</paper>

 <paper id="1030">
 <title>A Situated Perspective on Natural-Language Processing</title>
 <author><first>Susan U.</first><last>Stucky</last></author>
</paper>

 <paper id="1031">
 <title>Reference and Pragmatic Identification</title>
 <author><first>Douglas E.</first><last>Appe</last></author>
</paper>

 <paper id="1032">
 <title>Determiners, Entities, and Contexts</title>
 <author><first>Deborah A.</first><last>Dahl</last></author>
</paper>

 <paper id="1033">
 <title>Position Paper: Event Reference</title>
 <author><first>Bonnie Lynn</first><last>Webb</last></author>
</paper>

 <paper id="1034">
 <title>Goals of Referring Acts</title>
 <author><first>Amichai</first><last>Kronfeld</last></author>
</paper>

 <paper id="1035">
 <title>Reference and Reference Failures</title>
 <author><first>Bradley A.</first><last>Goodman</last></author>
</paper>

 <paper id="1036">
 <title>METAPHOR: THE GOOD, THE BAD AND THE UGLY</title>
 <author><first>Dedre</first><last>Gentner</last></author>
 <author><first>Bdan</first><last>Faikenhain</last></author>
</paper>

 <paper id="1037">
 <title>THE ROLE OF METAPHORS IN DESCRIPTIONS OF EMOTIONS</title>
 <author><first>Andrew</first><last>Ortony</last></author>
 <author><first>Lynn</first><last>Fainsilber</last></author>
</paper>

 <paper id="1038">
 <title>Mental Models and Metaphor</title>
 <author><first>Edwin</first><last>Plantin</last></author>
</paper>

 <paper id="1039">
 <title>Position Paper on Metaphor</title>
 <author><first>George</first><last>Lakoff</last></author>
</paper>

 <paper id="1040">
 <title>Poetic and Prosaic Metaphors</title>
 <author><first>Geoffrey</first><last>Nunberg</last></author>
</paper>

 <paper id="1041">
 <title>GENERATION - A NEW FRONTIER OF NATURAL LANGUAGE PROCESSING?</title>
 <author><first>Aravind K.</first><last>Joshi</last></author>
</paper>

 <paper id="1042">
 <title>Bidirectional Grammars and the Design of Natural Language Generation Systems</title>
 <author><first>Douglas E.</first><last>Appe</last></author>
</paper>

 <paper id="1043">
 <title>Limits on the human sentence generator</title>
 <author><first>Anthony S.</first><last>Kroch</last></author>
</paper>

 <paper id="1044">
 <title>"No Better, but no Worse, than People"</title>
 <author><first>David D.</first><last>McDonald</last></author>
</paper>

 <paper id="1045">
 <title>What is Special About Natural Language Generation Research?</title>
 <author><first>William C.</first><last>Mann</last></author>
</paper>

 <paper id="1046">
 <title>Generation Systems Should Choose Their Words</title>
 <author><first>Mitchell</first><last>Marc</last></author>
</paper>

</volume>
