<?xml version='1.0' encoding='UTF-8'?>
<collection id="2008.ws">
  <event id="ws-2008">
    <colocated>
      <volume-id>W08-01</volume-id>
      <volume-id>W08-02</volume-id>
      <volume-id>W08-03</volume-id>
      <volume-id>W08-04</volume-id>
      <volume-id>W08-05</volume-id>
      <volume-id>W08-06</volume-id>
      <volume-id>W08-07</volume-id>
      <volume-id>W08-08</volume-id>
      <volume-id>W08-09</volume-id>
      <volume-id>W08-10</volume-id>
      <volume-id>W08-11</volume-id>
      <volume-id>W08-12</volume-id>
      <volume-id>W08-13</volume-id>
      <volume-id>W08-14</volume-id>
      <volume-id>W08-15</volume-id>
      <volume-id>W08-16</volume-id>
      <volume-id>W08-17</volume-id>
      <volume-id>W08-18</volume-id>
      <volume-id>W08-19</volume-id>
      <volume-id>W08-20</volume-id>
      <volume-id>W08-21</volume-id>
      <volume-id>W08-22</volume-id>
      <volume-id>W08-23</volume-id>
    </colocated>
  </event>
</collection>
