<volume id="T78">
 <paper id="1000">
 <title>Theoretical Issues in Natural Language Processing-2</title>
</paper>

 <paper id="1001">
 <title>Testing The Psychological Reality of a Representational Model</title>
 <author><first>Dedre</first><last>Gentner</last></author>
</paper>

 <paper id="1002">
 <title>What Makes Something “Ad Hoe”</title>
 <author><first>Roger C.</first><last>Schank</last></author>
</paper>

 <paper id="1003">
 <title>The Relation of Grammar to Cognition–a Synopsis</title>
 <author><first>Leonard</first><last>Talmy</last></author>
</paper>

 <paper id="1004">
 <title>On primitives, prototypes, and other semantic anomalies</title>
 <author><first>Terry</first><last>Winograd</last></author>
</paper>

 <paper id="1005">
 <title>Taxonomic Lattice Structures for Situation Recognition</title>
 <author><first>William A.</first><last>Woods</last></author>
</paper>

 <paper id="1006">
 <title>Description Formation and Discourse Model Synthesis</title>
 <author><first>Bonnie Lynn</first><last>Webber</last></author>
</paper>

 <paper id="1007">
 <title>The Processing of Referring Expressions within a Semantic Network</title>
 <author><first>John R.</first><last>Anderson</last></author>
</paper>

 <paper id="1008">
 <title>Reference Diaries</title>
 <author><first>Herbert H.</first><last>Clark</last></author>
 <author><first>Catherine</first><last>Marshall</last></author>
</paper>

 <paper id="1009">
 <title>Subsequent Reference: Syntactic and Rhetorical Constraints</title>
 <author><first>David D.</first><last>McDonald</last></author>
</paper>

 <paper id="1010">
 <title>Some Psycholinguistic Constraints on the Construction and Interpretation of Definite Descriptions</title>
 <author><first>Andrew</first><last>Ortony</last></author>
</paper>

 <paper id="1011">
 <title>BOUND  VARIABLES  AND OTHER  ANAPHORS</title>
 <author><first>Barbara H.</first><last>Partee</last></author>
</paper>

 <paper id="1012">
 <title>The Use of Focus as a Tool for Disambiguation of Definite Noun Phrases</title>
 <author><first>Candace L.</first><last>Sidner</last></author>
</paper>

 <paper id="1013">
 <title>FOCUSING IN DIALOG</title>
 <author><first>Barbara J.</first><last>Grosz</last></author>
</paper>

 <paper id="1014">
 <title>Topic Levels</title>
 <author><first>Joseph E.</first><last>Grimes</last></author>
</paper>

 <paper id="1015">
 <title>Toward a Rational Model of Discourse Comprehension</title>
 <author><first>Jerry L.</first><last>Morgan</last></author>
</paper>

 <paper id="1016">
 <title>ASSENT AND COMPLIANCE IN CHILDREN’S LANGUAGE COMPREHENSION</title>
 <author><first>David R.</first><last>Olson</last></author>
</paper>

 <paper id="1017">
 <title>Speech Acts as a Basis for Understanding Dialogue Coherence</title>
 <author><first>C. Raymond</first><last>Perrault</last></author>
 <author><first>James F.</first><last>Allen</last></author>
</paper>

 <paper id="1018">
 <title>A Framework for Comparing Language Experiences (with particular emphasis on: The Effect of Audience on Discourse Models)</title>
 <author><first>Andee Rubin</first><last>Bolt</last></author>
</paper>

 <paper id="1019">
 <title>Intentlonallty and Human Conversations</title>
 <author><first>Jaime G. Carbonell</first><last>Jr.</last></author>
</paper>

 <paper id="1020">
 <title>ON  THE   INTERDEPENDENCE   OF  LANGUAGE  AND  PERCEPTION</title>
 <author><first>David L.</first><last>Waltz</last></author>
</paper>

 <paper id="1021">
 <title>The Problem of Naming Shapes: Vision-Language Interface</title>
 <author><first>R.</first><last>Bajcsy</last></author>
 <author><first>A. K.</first><last>Joshi</last></author>
</paper>

 <paper id="1022">
 <title>An Argument about the Composition of Conceptual Structure</title>
 <author><first>Ray</first><last>Jackendoff</last></author>
</paper>

 <paper id="1023">
 <title>ON  THE   ONTOLOGICAL   STATUS   OF  VISUAL  MENTAL   IMAGES</title>
 <author><first>Stephen</first><last>Michael</last></author>
</paper>

 <paper id="1024">
 <title>What has language to do with perception?  Some speculations on the Lingua Mentis</title>
 <author><first>Zenon W.</first><last>Pylyshyn</last></author>
</paper>

 <paper id="1025">
 <title>SEMANTIC PRIMITIVES IN LANGUAGE AND VISION</title>
 <author><first>Yorick</first><last>Wilks</last></author>
</paper>

 <paper id="1026">
 <title>A NOTE ON PARTIAL MATCH OF DESCRIPTIONS. CAN ONE SIMULTANEOUSLY QUESTION (RETRIEVE) AND INFORM (UPDATE)?</title>
 <author><first>Aravind K.</first><last>Joshi</last></author>
</paper>

 <paper id="1027">
 <title>WITH A SPOON IN HAND THIS MUST BE THE EATING FRAME</title>
 <author><first>Eugene</first><last>Charniak</last></author>
</paper>

 <paper id="1028">
 <title>Fragments of a Theory of Human Plausible Reasoning</title>
 <author><first>Allan</first><last>Collins</last></author>
</paper>

 <paper id="1029">
 <title>INDIRECT RESPONSES TO LOADED QUESTIONS</title>
 <author><first>S. Jerrold</first><last>Kaplan</last></author>
</paper>

 <paper id="1030">
 <title>ON REASONING BY DEFAULT</title>
 <author><first>Raymond</first><last>Reiter</last></author>
</paper>

 <paper id="1031">
 <title>PATH-BASED AND NODE-BASED INFERENCE IN SEMANTIC NETWORKS</title>
 <author><first>Stuart C.</first><last>Shapiro</last></author>
</paper>

 <paper id="1032">
 <title>The Representation of Derivable Information in Memory: When What Might Have Been Left Unsaid Is Said</title>
 <author><first>Rand J.</first><last>Spiro</last></author>
 <author><first>Joseph</first><last>Esposito</last></author>
 <author><first>Richard J.</first><last>Vondruska</last></author>
</paper>

 <paper id="1033">
 <title>A Heuristic for Paradigms</title>
 <author><first>Joseph E.</first><last>Grimes</last></author>
</paper>

 <paper id="1034">
 <title>A Computational Account of Some Constraints on Language</title>
 <author><first>Mitchell</first><last>Marcus</last></author>
</paper>

 <paper id="1035">
 <title>REMARKS ON PROCESSING, CONSTRIAINTS, AND THE LEXICON</title>
 <author><first>Thomas</first><last>Wasow</last></author>
</paper>

 <paper id="1036">
 <title>List of questions suggested for consideration in each session</title>
</paper>


</volume>